core/__init__.py
core/basic.py
core/database.py
core/proxies.py
core/request.py
core/settings.py
core/thread_pool.py
core/tor_network.py
core/torrc.py
core/user_agent.py
core/winservice.py
core/examples/__init__.py
core/examples/request_example.py
core/examples/tor_service.py
examples/__init__.py
examples/request_example.py
examples/tor_service.py
crawler_core-1.10.dist-info/METADATA
crawler_core-1.10.dist-info/WHEEL
crawler_core-1.10.dist-info/top_level.txt
crawler_core-1.10.dist-info/RECORD
