Metadata-Version: 2.1
Name: crawler-core
Version: 1.10
Summary: Core programs for crawling
Home-page: https://bitbucket.org/DraganMatesic/crawler_core
Author: Dragan Matesic
Author-email: dragan.matesic@gmail.com
License: MIT
Platform: UNKNOWN
Requires-Dist: SQLAlchemy
Requires-Dist: pandas
Requires-Dist: requests
Requires-Dist: bs4
Requires-Dist: stem
Requires-Dist: pymssql
Requires-Dist: pyodbc
